stencila/__init__.py
stencila/hub/__init__.py
stencila/hub/api_client.py
stencila/hub/configuration.py
stencila/hub/exceptions.py
stencila/hub/model_utils.py
stencila/hub/rest.py
stencila/hub/api/__init__.py
stencila/hub/api/accounts_api.py
stencila/hub/api/dois_api.py
stencila/hub/api/emails_api.py
stencila/hub/api/features_api.py
stencila/hub/api/invites_api.py
stencila/hub/api/jobs_api.py
stencila/hub/api/nodes_api.py
stencila/hub/api/projects_api.py
stencila/hub/api/providers_api.py
stencila/hub/api/status_api.py
stencila/hub/api/tokens_api.py
stencila/hub/api/users_api.py
stencila/hub/api/workers_api.py
stencila/hub/apis/__init__.py
stencila/hub/model/__init__.py
stencila/hub/model/account_create.py
stencila/hub/model/account_image.py
stencila/hub/model/account_list.py
stencila/hub/model/account_retrieve.py
stencila/hub/model/account_team.py
stencila/hub/model/account_team_create.py
stencila/hub/model/account_team_update.py
stencila/hub/model/account_update.py
stencila/hub/model/account_user.py
stencila/hub/model/account_user_create.py
stencila/hub/model/account_user_patch.py
stencila/hub/model/doi.py
stencila/hub/model/email.py
stencila/hub/model/file.py
stencila/hub/model/file_list.py
stencila/hub/model/github_repo.py
stencila/hub/model/inline_response200.py
stencila/hub/model/inline_response2001.py
stencila/hub/model/inline_response20010.py
stencila/hub/model/inline_response20011.py
stencila/hub/model/inline_response20012.py
stencila/hub/model/inline_response20013.py
stencila/hub/model/inline_response20014.py
stencila/hub/model/inline_response20015.py
stencila/hub/model/inline_response20016.py
stencila/hub/model/inline_response20017.py
stencila/hub/model/inline_response20018.py
stencila/hub/model/inline_response20019.py
stencila/hub/model/inline_response2002.py
stencila/hub/model/inline_response2003.py
stencila/hub/model/inline_response2004.py
stencila/hub/model/inline_response2005.py
stencila/hub/model/inline_response2006.py
stencila.hub-4.47.19.dist-info/METADATA
stencila.hub-4.47.19.dist-info/WHEEL
stencila.hub-4.47.19.dist-info/top_level.txt
stencila.hub-4.47.19.dist-info/RECORD
