Metadata-Version: 2.1
Name: stencila.hub
Version: 4.47.19
Summary: Stencila Hub API
Home-page: https://pypi.org/project/stencila.hub/
Author: Stencila and contributors
Author-email: hello@stenci.la
License: Apache 2.0
Keywords: OpenAPI,OpenAPI-Generator,Stencila Hub API
Platform: UNKNOWN
Requires-Python: >=3.6
Requires-Dist: urllib3 (>=1.25.3)
Requires-Dist: python-dateutil
